<?xml version="1.0" encoding="UTF-8" standalone="yes"?>
<VersementRASRF xmlns:xsi="http://www.w3.org/2001/XMLSchema-instance" xsi:noNamespaceSchemaLocation="VersementRASRF.xsd">
  <identifiantFiscal>IF</identifiantFiscal>
  <exerciceFiscalDu>2022-1-1</exerciceFiscalDu>
  <exerciceFiscalAu>2022-12-31</exerciceFiscalAu>
  <annee>2022</annee>
  <mois>3</mois>
  <totalMntBrutLoyer>0</totalMntBrutLoyer>
  <totalMntRetenueSource>0</totalMntRetenueSource>
  <totalMntNetLoyer>0</totalMntNetLoyer>
  <listDetailRetenueRevFoncier/>
</VersementRASRF>