<?xml version="1.0" encoding="UTF-8" standalone="yes"?>
<VersementRASRF xmlns:xsi="http://www.w3.org/2001/XMLSchema-instance" xsi:noNamespaceSchemaLocation="VersementRASRF.xsd">
  <identifiantFiscal>IF</identifiantFiscal>
  <exerciceFiscalDu>2022-01-01</exerciceFiscalDu>
  <exerciceFiscalAu>2022-12-31</exerciceFiscalAu>
  <annee>2022</annee>
  <mois>4</mois>
  <totalMntBrutLoyer>72000.00</totalMntBrutLoyer>
  <totalMntRetenueSource>5400.00</totalMntRetenueSource>
  <totalMntNetLoyer>66600.00</totalMntNetLoyer>
  <listDetailRetenueRevFoncier>
    <DetailRetenueRevFoncier>
      <ifuBailleur>IF2</ifuBailleur>
      <numCNIBailleur>BB125874</numCNIBailleur>
      <numCEBailleur/>
      <nomPrenomBailleur>YASSINE TYEST</nomPrenomBailleur>
      <adresseBailleur>1000000</adresseBailleur>
      <adresseBien>123456</adresseBien>
      <typeBienBailleur>
        <code>LUC</code>
      </typeBienBailleur>
      <mntBrutLoyer>72000.00</mntBrutLoyer>
      <mntRetenueSource>5400.00</mntRetenueSource>
      <mntNetLoyer>66600.00</mntNetLoyer>
      <tauxRetenueRevFoncier>
        <code>TSR.10.2018</code>
      </tauxRetenueRevFoncier>
    </DetailRetenueRevFoncier>
  </listDetailRetenueRevFoncier>
</VersementRASRF>